unzip_aes.py
unzip_aes-0.1.2.dist-info/LICENSE
unzip_aes-0.1.2.dist-info/METADATA
unzip_aes-0.1.2.dist-info/WHEEL
unzip_aes-0.1.2.dist-info/entry_points.txt
unzip_aes-0.1.2.dist-info/top_level.txt
unzip_aes-0.1.2.dist-info/RECORD
